{"title":"Parallels 小贴士","grey":true,"shareable":true,"id":"guide/tip/mac/parallels/index","author":"Mr.Hope","cite":[],"content":[{"tag":"text","type":"tip","text":["您可以通过 Parallels Desktop 在搭载 Apple 芯片的 MacBook 上安装并运行 Windows 虚拟机。","如果您的 Mac 使用 Intel 芯片，为了更好的性能，我们推荐您使用“启动转换助理”安装双系统。"]},{"tag":"list","items":[{"text":"使用“启动转换助理”安装 Windows","icon":"idea","path":"guide/tip/mac/bootcamp/index"}]},{"tag":"list","items":[{"text":"安装 Parallels Desktop","icon":"idea","path":"guide/tip/mac/parallels/install"},{"text":"通过 Parallels Desktop 安装 Windows 11","icon":"windows","path":"guide/tip/mac/parallels/win11"},{"text":"使用 Parallels Desktop","icon":"intro","path":"guide/tip/mac/parallels/usage"},{"text":"Parallels Desktop 虚拟机网络设置","icon":"network","path":"guide/tip/mac/parallels/network"},{"text":"避免通过 PD Runner 延长试用期","icon":"alert","path":"guide/tip/mac/parallels/pd-runner"}]}],"time":"2022 年 8 月 21 日"}