{"title":"长春站-到本部-公交","icon":"bus","shareable":true,"id":"newcomer/arrival/train-jingyue/bus","author":"Mr.Hope","cite":[],"content":[{"tag":"text","type":"danger","text":["公交和地铁是同等价位的，只慢不快还折腾! 不要坐公交!"]},{"tag":"title","text":"路程流程"},{"tag":"ol","text":["请从南出站口出站","沿地下广场继续向南走走到人民大街北端","在右手边找到车站。","乘 160 路到东北师范大学站。"]},{"tag":"text","type":"danger","text":["下车的站名为站名东北师范大学，千万不要在动植物公园站或者体育场站下车，那个是本部校区!!!"]},{"tag":"title","text":"价格与时间"},{"tag":"text","text":["票价 2 元，车程约 1 小时。"]},{"tag":"title","text":"到达校门"},{"tag":"text","type":"tip","header":"2024 年报到校门","text":["2 号门和 4 号门，博硕路上的最东门和最西门。"]},{"tag":"ul","text":["请您下车后掉头向前行进约 150m (向西北)","走到十字路口出左转进入博硕路","继续行进 100m 即可到达 2 号门"]}],"time":"2024 年 8 月 15 日 17:31:26"}