{"title":"学科教学（语文）","icon":"about","shareable":true,"id":"school/chinese/subject/teach","cite":["https://chinese.nenu.edu.cn/kxyj/xkfx.htm"],"content":[{"tag":"title","text":"学科教学（语文）"},{"tag":"p","text":["学科教学（语文）隶属于教育学一级学科，主要包括语文课程建设、语文教学实施、语文教师专业发展等研究方向。该学科是东北师范大学“卓越教师培养计划”示范点，具有硕士学位授予权，符合课程修读和答辩要求的毕业生能够获得教育学硕士学位。学科师资力量雄厚，培养过程中实行“双导师制”，每位硕士生都配备“1位大学专业导师”和“1位中学语文名师”，两位导师协同合作指导。学科突出实践育人导向，建构了“教学能力训练”“学科知识转化”“教学实践创新”“自我反思提升”四位一体的人才培养机制，培养模式和实践成果获得高等教育国家级成果二等奖。修读本学科课程后，毕业生能够系统掌握语文课程与教学的基本学理、教学设计与实施的有效路径，以及语文教研方法和课堂管理策略，具有在中小学从事语文教学与研究的专业素养。该学科致力于培养信念坚实、知识扎实、为人踏实、作风朴实，具有较强语文教学素养和班级管理能力，能够积极履行立德树人使命的中学语文卓越教师，毕业生备受中小学校赞誉。"]}],"time":"2025 年 6 月 24 日 09:20:18"}